{
    "dataset": {
        "name": "CIL",
        "label_name": "neuron",
        "indices": [
            84,
            25,
            79,
            10,
            32,
            45,
            57,
            31,
            12,
            39,
            48,
            86,
            71
        ]
    },
    "individual": {
        "sequence": "[[0, 0, 0, 0, 0], [0, 0, 0, 0, 0], [31, 0, 0, 248, 183], [22, 0, 0, 63, 122], [27, 0, 1, 190, 138], [35, 1, 3, 0, 134], [2, 2, 5, 249, 185], [10, 1, 5, 108, 166], [1, 3, 1, 210, 56], [27, 4, 3, 137, 93], [37, 1, 0, 7, 92], [4, 1, 8, 202, 5], [40, 3, 9, 137, 21], [14, 0, 10, 118, 153], [5, 6, 0, 191, 21], [4, 12, 7, 39, 12], [19, 8, 7, 12, 134], [3, 5, 2, 36, 13], [31, 0, 0, 155, 119], [14, 4, 13, 90, 154], [40, 14, 1, 14, 57], [4, 2, 6, 174, 10], [40, 20, 11, 131, 71], [24, 19, 20, 79, 33], [37, 7, 8, 102, 34], [18, 16, 17, 52, 3], [21, 10, 21, 226, 208], [19, 5, 3, 29, 142], [7, 6, 1, 36, 132], [37, 9, 7, 249, 66], [0, 6, 15, 48, 51], [33, 20, 15, 33, 98], [0, 21, 0, 0, 0], [0, 25, 0, 0, 0]]",
        "fitness": {
            "fitness": 0.13117218017578125,
            "time": 0.032889567888700046
        }
    },
    "decoding": {
        "metadata": {
            "rows": 1,
            "columns": 30,
            "n_in": 2,
            "n_out": 2,
            "n_para": 2,
            "n_conn": 2
        },
        "functions": [
            "max",
            "min",
            "mean",
            "add",
            "subtract",
            "bitwise_not",
            "bitwise_or",
            "bitwise_and",
            "bitwise_and_mask",
            "bitwise_xor",
            "sqrt",
            "pow2",
            "exp",
            "log",
            "median_blur",
            "gaussian_blur",
            "laplacian",
            "sobel",
            "robert_cross",
            "canny",
            "sharpen",
            "gabor",
            "abs_diff",
            "abs_diff2",
            "fluo_tophat",
            "rel_diff",
            "erode",
            "dilate",
            "open",
            "close",
            "morph_gradient",
            "morph_tophat",
            "morph_blackhat",
            "fill_holes",
            "remove_small_objects",
            "remove_small_holes",
            "threshold",
            "threshold_at_1",
            "distance_transform",
            "distance_transform_and_thresh",
            "inrange_bin",
            "inrange"
        ],
        "endpoint": {
            "name": "Marker-Based Watershed",
            "abbv": "WSHD",
            "arity": 2,
            "p": 0,
            "kwargs": {
                "use_dt": false,
                "markers_distance": 21,
                "markers_area": null
            }
        },
        "mode": "default"
    }
}