{
    "dataset": {
        "name": "Tumor",
        "label_name": "tumor",
        "indices": null
    },
    "individual": {
        "sequence": "[[0, 0, 0, 0, 0], [0, 0, 0, 0, 0], [0, 0, 0, 0, 0], [39, 1, 2, 16, 73], [8, 3, 0, 61, 112], [33, 1, 4, 176, 191], [8, 1, 4, 15, 190], [24, 6, 0, 174, 140], [4, 7, 0, 19, 117], [7, 8, 7, 31, 65], [21, 5, 7, 200, 22], [25, 8, 10, 77, 143], [32, 9, 11, 98, 4], [18, 11, 11, 232, 57], [21, 8, 3, 111, 161], [15, 12, 7, 60, 223], [29, 15, 14, 165, 82], [6, 15, 9, 71, 156], [0, 3, 5, 38, 158], [13, 15, 2, 29, 82], [5, 8, 8, 182, 174], [25, 14, 18, 63, 179], [21, 0, 8, 188, 241], [33, 19, 8, 51, 38], [28, 23, 9, 61, 137], [38, 17, 0, 87, 172], [25, 18, 2, 145, 180], [4, 0, 22, 88, 232], [41, 9, 15, 126, 41], [7, 2, 12, 237, 77], [1, 26, 20, 182, 22], [39, 23, 28, 41, 96], [8, 17, 27, 101, 24], [0, 24, 0, 0, 0]]",
        "fitness": {
            "fitness": 0.11689806403380204,
            "time": 0.09312760829925537
        }
    },
    "decoding": {
        "metadata": {
            "rows": 1,
            "columns": 30,
            "n_in": 3,
            "n_out": 1,
            "n_para": 2,
            "n_conn": 2
        },
        "functions": [
            "max",
            "min",
            "mean",
            "add",
            "subtract",
            "bitwise_not",
            "bitwise_or",
            "bitwise_and",
            "bitwise_and_mask",
            "bitwise_xor",
            "sqrt",
            "pow2",
            "exp",
            "log",
            "median_blur",
            "gaussian_blur",
            "laplacian",
            "sobel",
            "robert_cross",
            "canny",
            "sharpen",
            "gabor",
            "abs_diff",
            "abs_diff2",
            "fluo_tophat",
            "rel_diff",
            "erode",
            "dilate",
            "open",
            "close",
            "morph_gradient",
            "morph_tophat",
            "morph_blackhat",
            "fill_holes",
            "remove_small_objects",
            "remove_small_holes",
            "threshold",
            "threshold_at_1",
            "distance_transform",
            "distance_transform_and_thresh",
            "inrange_bin",
            "inrange"
        ],
        "endpoint": {
            "name": "Threshold (t=4)",
            "abbv": "TRSH",
            "arity": 1,
            "p": 0,
            "kwargs": {
                "threshold": 4
            }
        },
        "mode": "default"
    }
}